air2neo/__init__.py
air2neo/config.py
air2neo/main.py
air2neo/neo4j_operations.py
air2neo/py.typed
air2neo/utils.py
air2neo-2.2.0.dist-info/licenses/LICENSE
air2neo-2.2.0.dist-info/METADATA
air2neo-2.2.0.dist-info/WHEEL
air2neo-2.2.0.dist-info/top_level.txt
air2neo-2.2.0.dist-info/RECORD
