Metadata-Version: 2.4
Name: air2neo
Version: 2.2.0
Summary: Airtable to Neo4j Data Ingestor written in Python
Home-page: https://github.com/bilbyai/air2neo
Author: David Lee
License: BSD 3-Clause License
Keywords: airtable,neo4j,pyairtable,job,data,ingestor,air2neo,pipeline
Platform: unix
Platform: linux
Platform: osx
Platform: cygwin
Platform: win32
Classifier: Intended Audience :: Developers
Classifier: Topic :: Software Development
Classifier: Programming Language :: Python
Classifier: Programming Language :: Python :: 3
Classifier: Programming Language :: Python :: 3 :: Only
Classifier: Programming Language :: Python :: 3.10
Classifier: Programming Language :: Python :: 3.11
Classifier: Programming Language :: Python :: 3.12
License-File: LICENSE
Requires-Dist: pyairtable>=3.0.2
Requires-Dist: neo4j>=5.28.1
Requires-Dist: pandas>=2.2.3
Requires-Dist: pyarrow>=19.0.1
Dynamic: license-file
